Workbook

Sheet Custos
A1: Lanche Já · investimento e custos
A3: Investimento inicial | B3: Valor
A4: Chapa e estufa | B4: 4800
A5: Freezer usado | B5: 1500
A6: Tablet do balcão | B6: 1200
A7: Reforma do balcão | B7: 500
A8: Capital de giro (folga para os primeiros meses) | B8: 2000
A9: Total do investimento | B9: =SUM(B4:B8)
A11: Custos fixos por mês | B11: Valor
A12: Aluguel do espaço | B12: 1000
A13: Pró-labore do sócio | B13: 1200
A14: Energia e gás | B14: 300
A15: Internet | B15: 100
A16: Hospedagem do site e banco de dados | B16: 60
A17: Imposto do MEI (DAS) | B17: 80
A18: Divulgação | B18: 260
A19: Total dos custos fixos | B19: =SUM(B12:B18)
A22: Custo variável por combo | B22: Valor
A23: Ingredientes | B23: 4.9
A24: Embalagem | B24: 0.6
A25: Taxa do cartão e do Pix | B25: 0.5
A26: Total do custo variável | B26: =SUM(B23:B25)
A28: Preço do combo | B28: 16

Sheet Fluxo
A1: Lanche Já · fluxo de caixa projetado (12 meses)
A3: Linha | B3: Mês 1 | C3: Mês 2 | D3: Mês 3 | E3: Mês 4 | F3: Mês 5 | G3: Mês 6 | H3: Mês 7 | I3: Mês 8 | J3: Mês 9 | K3: Mês 10 | L3: Mês 11 | M3: Mês 12
A4: Combos vendidos | B4: 200 | C4: 250 | D4: 300 | E4: 350 | F4: 400 | G4: 450 | H4: 500 | I4: 500 | J4: 500 | K4: 500 | L4: 500 | M4: 500
A5: Receita | B5: =B4*Custos!$B$28 | C5: =C4*Custos!$B$28 | D5: =D4*Custos!$B$28 | E5: =E4*Custos!$B$28 | F5: =F4*Custos!$B$28 | G5: =G4*Custos!$B$28 | H5: =H4*Custos!$B$28 | I5: =I4*Custos!$B$28 | ... M5: =M4*Custos!$B$28
A6: (−) Custos variáveis | B6: =B4*Custos!$B$26 | C6: =C4*Custos!$B$26 | D6: =D4*Custos!$B$26 | E6: =E4*Custos!$B$26 | F6: =F4*Custos!$B$26 | G6: =G4*Custos!$B$26 | H6: =H4*Custos!$B$26 | I6: =I4*Custos!$B$26 | ... M6: =M4*Custos!$B$26
A7: (−) Custos fixos | B7: =Custos!$B$19 | C7: =Custos!$B$19 | D7: =Custos!$B$19 | E7: =Custos!$B$19 | F7: =Custos!$B$19 | G7: =Custos!$B$19 | H7: =Custos!$B$19 | I7: =Custos!$B$19 | ... M7: =Custos!$B$19
A8: Saldo do mês | B8: =B5-B6-B7 | C8: =C5-C6-C7 | D8: =D5-D6-D7 | E8: =E5-E6-E7 | F8: =F5-F6-F7 | G8: =G5-G6-G7 | H8: =H5-H6-H7 | I8: =I5-I6-I7 | ... M8: =M5-M6-M7
A9: Saldo acumulado | B9: =-Custos!$B$9+B8 | C9: =B9+C8 | D9: =C9+D8 | E9: =D9+E8 | F9: =E9+F8 | G9: =F9+G8 | H9: =G9+H8 | I9: =H9+I8 | J9: =I9+J8 | ... M9: =L9+M8

Sheet Indicadores
A1: Lanche Já · indicadores
A3: Indicador | B3: Resultado | C3: Como ler
A4: Margem de contribuição por combo | B4: =Custos!B28-Custos!B26 | C4: o que sobra de cada combo para pagar o fixo
A5: Ponto de equilíbrio (combos por mês) | B5: =ROUNDUP(Custos!B19/B4,0) | C5: abaixo disso, o mês dá prejuízo
A6: Ponto de equilíbrio (combos por dia, 20 dias) | B6: =ROUNDUP(B5/20,0) | C6: a meta diária do balcão
A7: Lucratividade (mês 12) | B7: =Fluxo!M8/Fluxo!M5 | C7: de cada R$ 1 vendido, quanto sobra
A8: Rentabilidade (1º ano) | B8: =SUM(Fluxo!B8:M8)/Custos!B9 | C8: quanto o investimento rendeu no ano
A9: Payback simples (meses) | B9: =Custos!B9/Fluxo!M8 | C9: investimento ÷ lucro de um mês cheio
A10: Payback pelo fluxo de caixa (mês) | B10: =COUNTIF(Fluxo!B9:M9,"<0")+1 | C10: o mês em que o saldo acumulado fica positivo

Sheet Cenários
A1: Lanche Já · análise de sensibilidade
A3: Premissa (mês cheio) | B3: Pessimista | C3: Realista | D3: Otimista
A4: Combos vendidos por mês | B4: 350 | C4: 500 | D4: 600
A5: Preço do combo | B5: 16 | C5: =Custos!B28 | D5: 16
A6: Custo variável por combo | B6: 6.6 | C6: =Custos!B26 | D6: =Custos!B26
A7: Custos fixos por mês | B7: =Custos!B19 | C7: =Custos!B19 | D7: =Custos!B19
A8: Margem por combo | B8: =B5-B6 | C8: =C5-C6 | D8: =D5-D6
A9: Lucro do mês | B9: =B4*B8-B7 | C9: =C4*C8-C7 | D9: =D4*D8-D7
A10: Ponto de equilíbrio (combos) | B10: =ROUNDUP(B7/B8,0) | C10: =ROUNDUP(C7/C8,0) | D10: =ROUNDUP(D7/D8,0)
A11: Payback simples (meses) | B11: =IF(B9<=0,"não se paga",Custos!$B$9/B9) | C11: =IF(C9<=0,"não se paga",Custos!$B$9/C9) | D11: =IF(D9<=0,"não se paga",Custos!$B$9/D9)
A13: Uma variável por vez (a partir do realista)
A14: Mudança | B14: Lucro do mês | C14: Variação do lucro
A15: Vendas 10% menores | B15: =($C$4*0.9)*($C$5-$C$6)-$C$7 | C15: =B15/$C$9-1
A16: Preço 10% menor | B16: =$C$4*($C$5*0.9-$C$6)-$C$7 | C16: =B16/$C$9-1
A17: Custo variável 10% maior | B17: =$C$4*($C$5-$C$6*1.1)-$C$7 | C17: =B17/$C$9-1
A18: Custos fixos 10% maiores | B18: =$C$4*($C$5-$C$6)-$C$7*1.1 | C18: =B18/$C$9-1
